Metadata-Version: 2.1
Name: polar-route
Version: 1.0.0
Summary: PolarRoute: Long-distance maritime polar route planning taking into account complex changing environmental conditions
Author-email: "Autonomous Marine Operations Planning (AMOP) Team, AI Lab, British Antarctic Survey" <amop@bas.ac.uk>
License: MIT License
Project-URL: Homepage, https://www.bas.ac.uk/project/autonomous-marine-operations-planning
Project-URL: Documentation, https://antarctica.github.io/PolarRoute
Project-URL: Repository, https://github.com/antarctica/PolarRoute
Project-URL: Issues, https://github.com/antarctica/PolarRoute/issues
Keywords: Polar Science,Marine Routing,Marine Science,Marine Operations
Classifier: Intended Audience :: Science/Research
Classifier: Development Status :: 4 - Beta
Classifier: License :: OSI Approved :: MIT License
Classifier: Natural Language :: English
Classifier: Operating System :: OS Independent
Classifier: Programming Language :: Python
Classifier: Programming Language :: Python :: 3
Classifier: Programming Language :: Python :: 3.8
Classifier: Programming Language :: Python :: 3.9
Classifier: Programming Language :: Python :: 3.10
Classifier: Programming Language :: Python :: 3.11
Classifier: Programming Language :: Python :: 3.12
Classifier: Programming Language :: Python :: 3.13
Classifier: Programming Language :: Python :: 3.14
Requires-Python: >=3.8
License-File: LICENSE
Requires-Dist: meshiphi ==2.1.13
Requires-Dist: dask
Requires-Dist: geopandas
Requires-Dist: jsonschema
Requires-Dist: matplotlib
Requires-Dist: netcdf4
Requires-Dist: numpy >=1.21.6
Requires-Dist: pandas >=1.3.5
Requires-Dist: pyproj
Requires-Dist: pytest
Requires-Dist: shapely
Requires-Dist: scikit-learn
Requires-Dist: scipy
Requires-Dist: tqdm
Requires-Dist: xarray
Requires-Dist: fiona
Provides-Extra: test
Requires-Dist: pytest ; extra == 'test'
